endesive/__init__.py
endesive/hsm.py
endesive/signer.py
endesive/verifier.py
endesive/email/__init__.py
endesive/email/decrypt.py
endesive/email/encrypt.py
endesive/email/sign.py
endesive/email/verify.py
endesive/pdf/__init__.py
endesive/pdf/cms.py
endesive/pdf/pdf.py
endesive/pdf/verify.py
endesive/pdf/PyPDF2/__init__.py
endesive/pdf/PyPDF2/_version.py
endesive/pdf/PyPDF2/filters.py
endesive/pdf/PyPDF2/generic.py
endesive/pdf/PyPDF2/merger.py
endesive/pdf/PyPDF2/pagerange.py
endesive/pdf/PyPDF2/pdf.py
endesive/pdf/PyPDF2/utils.py
endesive/pdf/PyPDF2/xmp.py
endesive/pdf/PyPDF2_annotate/__init__.py
endesive/pdf/PyPDF2_annotate/annotator.py
endesive/pdf/PyPDF2_annotate/graphics.py
endesive/pdf/PyPDF2_annotate/pdfrw.py
endesive/pdf/PyPDF2_annotate/pdfttf.py
endesive/pdf/PyPDF2_annotate/annotations/__init__.py
endesive/pdf/PyPDF2_annotate/annotations/base.py
endesive/pdf/PyPDF2_annotate/annotations/image.py
endesive/pdf/PyPDF2_annotate/annotations/points.py
endesive/pdf/PyPDF2_annotate/annotations/rect.py
endesive/pdf/PyPDF2_annotate/annotations/signature.py
endesive/pdf/PyPDF2_annotate/annotations/text.py
endesive/pdf/PyPDF2_annotate/config/__init__.py
endesive/pdf/PyPDF2_annotate/config/appearance.py
endesive/pdf/PyPDF2_annotate/config/constants.py
endesive/pdf/PyPDF2_annotate/config/graphics_state.py
endesive/pdf/PyPDF2_annotate/config/location.py
endesive/pdf/PyPDF2_annotate/config/metadata.py
endesive/pdf/PyPDF2_annotate/fonts/Helvetica.ttf
endesive/pdf/PyPDF2_annotate/fonts/__init__.py
endesive/pdf/PyPDF2_annotate/util/__init__.py
endesive/pdf/PyPDF2_annotate/util/font_metrics.py
endesive/pdf/PyPDF2_annotate/util/geometry.py
endesive/pdf/PyPDF2_annotate/util/text.py
endesive/pdf/PyPDF2_annotate/util/true_type_font.py
endesive/pdf/PyPDF2_annotate/util/validation.py
endesive/pdf/fpdf/__init__.py
endesive/pdf/fpdf/fonts.py
endesive/pdf/fpdf/fpdf.py
endesive/pdf/fpdf/html.py
endesive/pdf/fpdf/php.py
endesive/pdf/fpdf/py3k.py
endesive/pdf/fpdf/template.py
endesive-2.19.2.dist-info/licenses/LICENSE
endesive-2.19.2.dist-info/licenses/LICENSE.pdf-annotate
endesive-2.19.2.dist-info/licenses/LICENSE.pyfpdf
endesive-2.19.2.dist-info/licenses/LICENSE.pypdf2
endesive-2.19.2.dist-info/METADATA
endesive-2.19.2.dist-info/WHEEL
endesive-2.19.2.dist-info/top_level.txt
endesive-2.19.2.dist-info/RECORD
