Metadata-Version: 2.4
Name: endesive
Version: 2.19.2
Summary: Library for digital signing and verification of digital signatures in mail, PDF and XML documents.
Author-email: Grzegorz Makarewicz <mak@trisoft.com.pl>
Maintainer-email: Grzegorz Makarewicz <mak@trisoft.com.pl>
License-Expression: MIT
Project-URL: Source, https://github.com/m32/endesive
Project-URL: Bug Reports, https://github.com/m32/endesive/issues
Classifier: Development Status :: 4 - Beta
Classifier: Development Status :: 5 - Production/Stable
Classifier: Operating System :: OS Independent
Classifier: Intended Audience :: Developers
Classifier: Programming Language :: Python :: 3
Classifier: Topic :: Software Development :: Libraries :: Python Modules
Classifier: Topic :: Communications :: Email
Classifier: Topic :: Security :: Cryptography
Classifier: Topic :: Office/Business
Classifier: Topic :: Text Processing
Classifier: Topic :: Multimedia :: Graphics
Requires-Python: >=3.0
License-File: LICENSE
License-File: LICENSE.pdf-annotate
License-File: LICENSE.pyfpdf
License-File: LICENSE.pypdf2
Provides-Extra: full
Requires-Dist: cryptography; extra == "full"
Requires-Dist: asn1crypto; extra == "full"
Requires-Dist: lxml; extra == "full"
Requires-Dist: pykcs11; extra == "full"
Requires-Dist: Pillow; extra == "full"
Requires-Dist: requests; extra == "full"
Requires-Dist: paramiko; extra == "full"
Provides-Extra: dev
Requires-Dist: pytest-cov; extra == "dev"
Requires-Dist: wheel; extra == "dev"
Provides-Extra: docs
Requires-Dist: sphinx; extra == "docs"
Requires-Dist: sphinx_rtd_theme; extra == "docs"
Dynamic: license-file
